pymessenger4/__init__.py
pymessenger4/bot.py
pymessenger4/utils.py
pymessenger4-1.0.1.dist-info/LICENSE
pymessenger4-1.0.1.dist-info/METADATA
pymessenger4-1.0.1.dist-info/WHEEL
pymessenger4-1.0.1.dist-info/top_level.txt
pymessenger4-1.0.1.dist-info/RECORD
